prom_url_checker/__init__.py
prom_url_checker/app.py
prom_url_checker/exceptions.py
prom_url_checker/utils/__init__.py
prom_url_checker/utils/_asyncio.py
prom_url_checker/utils/_logging.py
prom_url_checker/utils/server.py
prom_url_checker-0.0.4.dist-info/entry_points.txt
prom_url_checker-0.0.4.dist-info/LICENSE
prom_url_checker-0.0.4.dist-info/WHEEL
prom_url_checker-0.0.4.dist-info/METADATA
prom_url_checker-0.0.4.dist-info/RECORD
