Metadata-Version: 2.1
Name: prom-url-checker
Version: 0.0.4
Summary: Prom-url-checker, a url checker with prometheus metrics output
Home-page: https://github.com/datalyze-solutions/prom-url-checker
License: UNKNOWN
Keywords: http domain url monitoring prometheus check
Author: Matthias Ludwig
Author-email: m.ludwig@datalyze-solutions.com
Requires-Python: >=3.6
Classifier: Development Status :: 3 - Alpha
Classifier: Intended Audience :: Developers
Classifier: License :: OSI Approved :: MIT License
Classifier: Natural Language :: English
Classifier: Operating System :: POSIX :: Linux
Classifier: Operating System :: Microsoft
Classifier: Operating System :: MacOS
Classifier: Programming Language :: Python :: 3.6
Classifier: Programming Language :: Python :: 3.7
Classifier: Topic :: System :: Networking :: Monitoring
Requires-Dist: clize==4
Requires-Dist: aiohttp==3.5.4
Requires-Dist: aioprometheus==18.7.1
Requires-Dist: black; extra == "dev"
Requires-Dist: bumpversion; extra == "dev"
Requires-Dist: flake8; extra == "dev"
Requires-Dist: flit; extra == "dev"
Requires-Dist: mypy; extra == "dev"
Requires-Dist: mkdocs; extra == "doc"
Requires-Dist: pytest; extra == "test"
Requires-Dist: pytest-cov; extra == "test"
Requires-Dist: pytest-asyncio; extra == "test"
Requires-Dist: pytest-aiohttp; extra == "test"
Requires-Dist: tox; extra == "test"
Provides-Extra: dev
Provides-Extra: doc
Provides-Extra: test
